verysimplemodule_alisonVitorH/__init__.py
verysimplemodule_alisonVitorH/add.py
verysimplemodule_alisonVitorH/subtract.py
verysimplemodule_alisonVitorH/extra/__init__.py
verysimplemodule_alisonVitorH/extra/divide.py
verysimplemodule_alisonVitorH/extra/multiple.py
verysimplemodule_alisonVitorH-0.0.7.dist-info/METADATA
verysimplemodule_alisonVitorH-0.0.7.dist-info/WHEEL
verysimplemodule_alisonVitorH-0.0.7.dist-info/top_level.txt
verysimplemodule_alisonVitorH-0.0.7.dist-info/RECORD
