Metadata-Version: 2.1
Name: verysimplemodule_alisonVitorH
Version: 0.0.7
Summary: My first Python package
Author: Alison
Author-email: alissonmarqueshm30@gmail.com
